ukpostcodeio/__init__.py
ukpostcodeio/client.py
ukpostcodeio/exceptions.py
ukpostcodeio-1.0.0.dist-info/LICENSE
ukpostcodeio-1.0.0.dist-info/METADATA
ukpostcodeio-1.0.0.dist-info/WHEEL
ukpostcodeio-1.0.0.dist-info/top_level.txt
ukpostcodeio-1.0.0.dist-info/RECORD
