Metadata-Version: 2.1
Name: ukpostcodeio
Version: 1.0.0
Summary: A Python client for the Postcodes.io API used for UK postcodes
Home-page: https://github.com/ymrohit/ukpostcodeio
Author: Rohit Yelukati Mahendra
Author-email: Rohit Yelukati Mahendra <rohityelukati@gmail.com>
License: MIT
Keywords: postcode,uk,postcodes.io,api,client
Classifier: Programming Language :: Python :: 3
Classifier: Programming Language :: Python :: 3.7
Classifier: Programming Language :: Python :: 3.8
Classifier: Programming Language :: Python :: 3.9
Classifier: Programming Language :: Python :: 3.10
Classifier: Programming Language :: Python :: 3.11
Classifier: Operating System :: OS Independent
Classifier: License :: OSI Approved :: MIT License
Classifier: Intended Audience :: Developers
Classifier: Topic :: Software Development :: Libraries
Requires-Python: >=3.7
License-File: LICENSE
Requires-Dist: requests>=2.23.3
